rcli/__init__.py
rcli/__main__.py
rcli/brect.py
rcli/components.py
rcli/cursedcli.py
rcli/enums.py
rcli/forms.py
rcli/rcli.py
rcli/rclone.py
rcli/scenes.py
rclonecli-1.2.0.dist-info/licenses/LICENSE
rclonecli-1.2.0.dist-info/METADATA
rclonecli-1.2.0.dist-info/WHEEL
rclonecli-1.2.0.dist-info/entry_points.txt
rclonecli-1.2.0.dist-info/top_level.txt
rclonecli-1.2.0.dist-info/RECORD
