Metadata-Version: 2.4
Name: rclonecli
Version: 1.2.0
Summary: A CLI Interface for rclone
Project-URL: Homepage, https://github.com/Desperationis/rcli
Project-URL: Issues, https://github.com/Desperationis/rcli/issues
Classifier: Programming Language :: Python :: 3
Classifier: License :: OSI Approved :: MIT License
Requires-Python: >=3.9
License-File: LICENSE
Requires-Dist: docopt>=0.6.2
Dynamic: license-file
